{"Table":{"TableRDC":{"TableML":{"Columns":[],"Indexes":[],"DefaultData":[],"Name":null,"ProjectName":null,"SchemaName":null,"DDLName":null,"ForeignKeys":[]},"Columns":[],"Indexes":[],"DefaultData":[],"Name":null,"ProjectName":null,"SchemaName":null,"DDLName":null,"ForeignKeys":[]},"TableRD":{"Columns":[],"Indexes":[],"DefaultData":[],"Name":null,"ProjectName":null,"SchemaName":null,"DDLName":null,"ForeignKeys":[]},"Name":"E_damlaucus_Form2","SchemaName":"dbo","TablePrefix":"damlaucus","TableML":{"Columns":[],"Indexes":[],"DefaultData":[],"Name":null,"ProjectName":null,"SchemaName":null,"DDLName":null,"ForeignKeys":[]},"DetailTables":[{"TableML":{"Columns":[{"size":50,"typeName":"StringDataColumn","type":16,"allowNull":true,"name":"SEHIRLER","prefix":null}],"Indexes":[],"DefaultData":[],"Name":null,"ProjectName":null,"SchemaName":null,"DDLName":null,"ForeignKeys":[]},"Name":"E_damlaucus_Form2_DataGrid1","ParentFormName":"Form2","TableRDC":{"TableML":{"Columns":[],"Indexes":[],"DefaultData":[],"Name":null,"ProjectName":null,"SchemaName":null,"DDLName":null,"ForeignKeys":[]},"Columns":[],"Indexes":[],"DefaultData":[],"Name":null,"ProjectName":null,"SchemaName":null,"DDLName":null,"ForeignKeys":[]},"TableRD":{"Columns":[],"Indexes":[],"DefaultData":[],"Name":null,"ProjectName":null,"SchemaName":null,"DDLName":null,"ForeignKeys":[]},"SchemaName":"dbo","TablePrefix":"damlaucus","DetailTables":[],"SelectControlNames":[],"FishBoneControlNames":[],"Columns":[{"precision":0,"size":16,"typeName":"NumericDataColumn","type":7,"allowNull":true,"name":"DGID","prefix":null},{"precision":5,"size":19,"typeName":"NumericDataColumn","type":7,"allowNull":true,"name":"ENLEM","prefix":null},{"precision":5,"size":19,"typeName":"NumericDataColumn","type":7,"allowNull":true,"name":"BOYLAM","prefix":null}],"Indexes":[],"DefaultData":[],"ProjectName":"damlaucus","DDLName":"DataGrid1","ForeignKeys":[]}],"SelectControlNames":[],"FishBoneControlNames":[],"Columns":[{"precision":2,"size":18,"typeName":"NumericDataColumn","type":7,"allowNull":false,"name":"BAGAJ","prefix":null},{"precision":2,"size":18,"typeName":"NumericDataColumn","type":7,"allowNull":false,"name":"MILUCRET","prefix":null},{"precision":2,"size":18,"typeName":"NumericDataColumn","type":7,"allowNull":false,"name":"NumberBox1","prefix":null}],"Indexes":[],"DefaultData":[],"ProjectName":"damlaucus","DDLName":"Form2","ForeignKeys":[]},"ProjectName":"damlaucus","TablePrefix":"damlaucus"}